[
  {
    "sessionId": "complete-cluster-report-67890",
    "timestamp": 1755184914591,
    "userMessage": "Tool oc_diagnostic_cluster_health executed with args: {\"includeNamespaceAnalysis\":true,\"maxNamespacesToAnalyze\":10}",
    "assistantResponse": "{\"cluster\":{\"status\":\"connected\",\"version\":\"4.18.1\",\"currentUser\":\"kube:admin\",\"serverUrl\":\".clusters[0].cluster.server\",\"timestamp\":\"2025-08-14T15:21:54.591Z\"},\"nodes\":{\"total\":4,\"ready\":4,\"issues\":[]},\"operators\":{\"total\":34,\"degraded\":[\"ingress\",\"monitoring\"]},\"systemNamespaces\":[{\"namespace\":\"openshift-apiserver\",\"status\":\"healthy\",\"issues\":0},{\"namespace\":\"openshift-etcd\",\"status\":\"degraded\",\"issues\":0},{\"namespace\":\"openshift-kube-apiserver\",\"status\":\"degraded\",\"issues\":0}],\"userNamespaces\":[{\"namespace\":\"default\",\"status\":\"failing\",\"podCount\":0,\"issues\":0},{\"namespace\":\"devops\",\"status\":\"failing\",\"podCount\":1,\"issues\":0},{\"namespace\":\"openshift\",\"status\":\"failing\",\"podCount\":0,\"issues\":0},{\"namespace\":\"student01\",\"status\":\"healthy\",\"podCount\":2,\"issues\":2},{\"namespace\":\"student02\",\"status\":\"healthy\",\"podCount\":0,\"issues\":2},{\"namespace\":\"student03\",\"status\":\"degraded\",\"podCount\":0,\"issues\":3},{\"namespace\":\"student04\",\"status\":\"healthy\",\"podCount\":0,\"issues\":2},{\"namespace\":\"student05\",\"status\":\"degraded\",\"podCount\":0,\"issues\":3},{\"namespace\":\"student06\",\"status\":\"degraded\",\"podCount\":0,\"issues\":3},{\"namespace\":\"student07\",\"status\":\"healthy\",\"podCount\":0,\"issues\":2}],\"overallHealth\":\"failing\",\"duration\":\"9698ms\",\"recommendations\":[\"Check degraded operators: oc get clusteroperator ingress -o yaml\"]}",
    "context": [],
    "tags": [
      "diagnostic",
      "cluster_health",
      "failing",
      "tool:oc_diagnostic_cluster_health",
      "domain:openshift",
      "environment:prod",
      "severity:medium",
      "domain:openshift",
      "environment:prod",
      "severity:medium",
      "resource:unknown"
    ]
  },
  {
    "sessionId": "complete-cluster-report-67890",
    "timestamp": 1755184917844,
    "userMessage": "Tool oc_diagnostic_namespace_health executed with args: {\"namespace\":\"student03\",\"includeIngressTest\":false}",
    "assistantResponse": "{\"tool\":\"check_namespace_health_v2\",\"sessionId\":\"complete-cluster-report-67890\",\"timestamp\":\"2025-08-14T15:21:57.844Z\",\"duration\":\"562ms\",\"namespace\":\"student03\",\"status\":\"degraded\",\"summary\":{\"pods\":\"0/0 ready\",\"pvcs\":\"1/2 bound\",\"routes\":\"1 configured\",\"criticalEvents\":0},\"issues\":{\"crashLoopPods\":[],\"imagePullErrors\":[],\"pendingPods\":[],\"oomKilledPods\":[],\"pvcErrors\":[\"pvc/shared-pvc pending (no storageclass or provisioner unavailable)\"],\"recentEvents\":[]},\"suspicions\":[\"📉 SCALE-DOWN: Detected scaling activity - verify if intentional\",\"Missing or invalid StorageClass - create default StorageClass or specify in PVC\",\"Scale-down evidence: Deployment code-server intentionally scaled to 0 replicas\"],\"connectivity\":{\"tested\":false},\"human\":\"Namespace student03 is degraded with scale-down activity detected. Storage: 1/2 PVCs bound. 1 PVC(s) pending. 1 route(s) configured. Key issue: 📉 SCALE-DOWN: Detected scaling activity - verify if intentional\",\"nextActions\":[\"Check PVC status: oc get pvc -n student03\",\"Verify storage class: oc get sc\"],\"performance\":{\"responseTime\":\"562ms\",\"cacheStats\":{\"size\":10,\"hitRate\":0.85}}}",
    "context": [],
    "tags": [
      "diagnostic",
      "namespace_health",
      "student03",
      "degraded",
      "tool:oc_diagnostic_namespace_health",
      "domain:openshift",
      "environment:prod",
      "severity:medium",
      "domain:openshift",
      "environment:prod",
      "severity:medium",
      "resource:unknown"
    ]
  },
  {
    "sessionId": "complete-cluster-report-67890",
    "timestamp": 1755184920064,
    "userMessage": "Tool oc_diagnostic_namespace_health executed with args: {\"namespace\":\"student05\",\"includeIngressTest\":false}",
    "assistantResponse": "{\"tool\":\"check_namespace_health_v2\",\"sessionId\":\"complete-cluster-report-67890\",\"timestamp\":\"2025-08-14T15:22:00.064Z\",\"duration\":\"538ms\",\"namespace\":\"student05\",\"status\":\"degraded\",\"summary\":{\"pods\":\"0/0 ready\",\"pvcs\":\"1/2 bound\",\"routes\":\"1 configured\",\"criticalEvents\":0},\"issues\":{\"crashLoopPods\":[],\"imagePullErrors\":[],\"pendingPods\":[],\"oomKilledPods\":[],\"pvcErrors\":[\"pvc/shared-pvc pending (no storageclass or provisioner unavailable)\"],\"recentEvents\":[]},\"suspicions\":[\"📉 SCALE-DOWN: Detected scaling activity - verify if intentional\",\"Missing or invalid StorageClass - create default StorageClass or specify in PVC\",\"Scale-down evidence: Deployment code-server intentionally scaled to 0 replicas\"],\"connectivity\":{\"tested\":false},\"human\":\"Namespace student05 is degraded with scale-down activity detected. Storage: 1/2 PVCs bound. 1 PVC(s) pending. 1 route(s) configured. Key issue: 📉 SCALE-DOWN: Detected scaling activity - verify if intentional\",\"nextActions\":[\"Check PVC status: oc get pvc -n student05\",\"Verify storage class: oc get sc\"],\"performance\":{\"responseTime\":\"538ms\",\"cacheStats\":{\"size\":15,\"hitRate\":0.85}}}",
    "context": [],
    "tags": [
      "diagnostic",
      "namespace_health",
      "student05",
      "degraded",
      "tool:oc_diagnostic_namespace_health",
      "domain:openshift",
      "environment:prod",
      "severity:medium",
      "domain:openshift",
      "environment:prod",
      "severity:medium",
      "resource:unknown"
    ]
  },
  {
    "sessionId": "complete-cluster-report-67890",
    "timestamp": 1755184922268,
    "userMessage": "Tool oc_diagnostic_namespace_health executed with args: {\"namespace\":\"default\",\"includeIngressTest\":false}",
    "assistantResponse": "{\"tool\":\"check_namespace_health_v2\",\"sessionId\":\"complete-cluster-report-67890\",\"timestamp\":\"2025-08-14T15:22:02.268Z\",\"duration\":\"527ms\",\"namespace\":\"default\",\"status\":\"failing\",\"summary\":{\"pods\":\"0/0 ready\",\"pvcs\":\"0/0 bound\",\"routes\":\"0 configured\",\"criticalEvents\":0},\"issues\":{\"crashLoopPods\":[],\"imagePullErrors\":[],\"pendingPods\":[],\"oomKilledPods\":[],\"pvcErrors\":[],\"recentEvents\":[]},\"suspicions\":[],\"connectivity\":{\"tested\":false},\"human\":\"Namespace default is failing.\",\"nextActions\":[\"Run detailed diagnostics: oc describe namespace default\"],\"performance\":{\"responseTime\":\"527ms\",\"cacheStats\":{\"size\":20,\"hitRate\":0.85}}}",
    "context": [],
    "tags": [
      "diagnostic",
      "namespace_health",
      "default",
      "failing",
      "tool:oc_diagnostic_namespace_health",
      "domain:openshift",
      "environment:prod",
      "severity:medium",
      "domain:openshift",
      "environment:prod",
      "severity:medium",
      "resource:unknown"
    ]
  },
  {
    "sessionId": "complete-cluster-report-67890",
    "timestamp": 1755184924281,
    "userMessage": "Tool oc_diagnostic_namespace_health executed with args: {\"namespace\":\"openshift\",\"includeIngressTest\":false}",
    "assistantResponse": "{\"tool\":\"check_namespace_health_v2\",\"sessionId\":\"complete-cluster-report-67890\",\"timestamp\":\"2025-08-14T15:22:04.281Z\",\"duration\":\"529ms\",\"namespace\":\"openshift\",\"status\":\"failing\",\"summary\":{\"pods\":\"0/0 ready\",\"pvcs\":\"0/0 bound\",\"routes\":\"0 configured\",\"criticalEvents\":0},\"issues\":{\"crashLoopPods\":[],\"imagePullErrors\":[],\"pendingPods\":[],\"oomKilledPods\":[],\"pvcErrors\":[],\"recentEvents\":[]},\"suspicions\":[],\"connectivity\":{\"tested\":false},\"human\":\"Namespace openshift is failing.\",\"nextActions\":[\"Run detailed diagnostics: oc describe namespace openshift\"],\"performance\":{\"responseTime\":\"529ms\",\"cacheStats\":{\"size\":25,\"hitRate\":0.85}}}",
    "context": [],
    "tags": [
      "diagnostic",
      "namespace_health",
      "openshift",
      "failing",
      "tool:oc_diagnostic_namespace_health",
      "domain:openshift",
      "environment:prod",
      "severity:medium",
      "domain:openshift",
      "environment:prod",
      "severity:medium",
      "resource:unknown"
    ]
  }
]